ezlog/__init__.py
ezlog/_types.py
ezlog/defaults.py
ezlog/exceptions.py
ezlog/handlers.py
ezlog/logger.py
ezlog/loggergroup.py
ezlog/utils.py
ezloglib-1.0.1.dist-info/LICENSE
ezloglib-1.0.1.dist-info/METADATA
ezloglib-1.0.1.dist-info/WHEEL
ezloglib-1.0.1.dist-info/top_level.txt
ezloglib-1.0.1.dist-info/RECORD
