Metadata-Version: 2.1
Name: ezloglib
Version: 1.0.1
Summary: Small modern colored logging library
Author-email: ftdot <ftdoot@gmail.com>
License: MIT License
Project-URL: Homepage, https://github.com/ftdot/ezlog
Project-URL: Documentation, https://ezlog.readthedocs.io/
Keywords: easy,colored,color,library,logging,logs
Classifier: Environment :: Plugins
Classifier: Framework :: Sphinx
Classifier: Natural Language :: English
Classifier: License :: OSI Approved :: MIT License
Classifier: Programming Language :: Python
Classifier: Programming Language :: Python :: 3
Classifier: Programming Language :: Python :: 3.9
Classifier: Programming Language :: Python :: 3.10
Classifier: Topic :: Documentation :: Sphinx
Classifier: Topic :: System :: Logging
Requires-Python: >=3.10
License-File: LICENSE
Requires-Dist: colorama
Provides-Extra: dev
Requires-Dist: sphinx ; extra == 'dev'
Requires-Dist: furo ; extra == 'dev'
